autogen/__init__.py
autogen/code_utils.py
autogen/math_utils.py
autogen/retrieve_utils.py
autogen/version.py
autogen/agentchat/__init__.py
autogen/agentchat/agent.py
autogen/agentchat/assistant_agent.py
autogen/agentchat/conversable_agent.py
autogen/agentchat/groupchat.py
autogen/agentchat/user_proxy_agent.py
autogen/agentchat/contrib/__init__.py
autogen/agentchat/contrib/math_user_proxy_agent.py
autogen/agentchat/contrib/qdrant_retrieve_user_proxy_agent.py
autogen/agentchat/contrib/retrieve_assistant_agent.py
autogen/agentchat/contrib/retrieve_user_proxy_agent.py
autogen/agentchat/contrib/teachable_agent.py
autogen/agentchat/contrib/text_analyzer_agent.py
autogen/cache/__init__.py
autogen/cache/abstract_cache_base.py
autogen/cache/cache.py
autogen/cache/cache_factory.py
autogen/cache/disk_cache.py
autogen/cache/redis_cache.py
autogen/extensions/__init__.py
autogen/oai/__init__.py
autogen/oai/completion.py
autogen/oai/openai_utils.py
guinsoft_pyautogen-0.3.2.dist-info/METADATA
guinsoft_pyautogen-0.3.2.dist-info/WHEEL
guinsoft_pyautogen-0.3.2.dist-info/top_level.txt
guinsoft_pyautogen-0.3.2.dist-info/RECORD
